{
  "nodes": [
    {
      "name": "On clicking 'execute'",
      "type": "n8n-nodes-base.manualTrigger",
      "position": [
        250,
        300
      ],
      "parameters": {},
      "typeVersion": 1
    },
    {
      "name": "Box",
      "type": "n8n-nodes-base.box",
      "position": [
        450,
        300
      ],
      "parameters": {
        "name": "n8n-rocks",
        "options": {},
        "resource": "folder"
      },
      "credentials": {
        "boxOAuth2Api": "box"
      },
      "typeVersion": 1
    }
  ],
  "connections": {
    "On clicking 'execute'": {
      "main": [
        [
          {
            "node": "Box",
            "type": "main",
            "index": 0
          }
        ]
      ]
    }
  },
  "_metadata": {
    "id": "",
    "name": "Untitled Workflow",
    "description": "",
    "source": "community-collection",
    "category": {
      "business": "",
      "platform": "",
      "type": "automation"
    },
    "metadata": {
      "complexity": "beginner",
      "department": "",
      "nodes_count": 2,
      "integrations": [
        "box",
        "manualTrigger"
      ],
      "estimated_cost": "medium",
      "security_level": "public"
    },
    "tags": [],
    "created_at": "2025-07-07T19:46:34.443596",
    "updated_at": "2025-07-07T19:46:34.443597",
    "version": "1.0.0"
  }
}